flask_ip_api/__init__.py
flask_ip_api-1.1.1.dist-info/LICENSE
flask_ip_api-1.1.1.dist-info/METADATA
flask_ip_api-1.1.1.dist-info/WHEEL
flask_ip_api-1.1.1.dist-info/top_level.txt
flask_ip_api-1.1.1.dist-info/RECORD
