Metadata-Version: 2.1
Name: flask-ip-api
Version: 1.1.1
Summary: Gives access to client IP information.
Home-page: https://github.com/EpicCodeWizard/Flask-IP-Info-Extension
Author: EpicCodeWizard
Author-email: epiccodewizard@gmail.com
License: UNKNOWN
Platform: UNKNOWN
Classifier: Programming Language :: Python :: 3
Classifier: License :: OSI Approved :: MIT License
Classifier: Operating System :: OS Independent
Requires-Dist: werkzeug
Requires-Dist: flask
Requires-Dist: requests
